Workbook
Name NewMatrix1: 'Correlation effect'!#REF!

Sheet Adjusted close
B1: Boeing Cie | C1: Lockheed Martin | D1: Intel Corp. | E1: Merck & Company | F1: AT&T | G1: Exelon | H1: GE | I1: Honeywell | J1: Schlumberger | K1: Avery
A2: Date | B2: Adj Close | C2: Adj Close | D2: Adj Close | E2: Adj Close | F2: Adj Close | G2: Adj Close | H2: Adj Close | I2: Adj Close | J2: Adj Close | K2: Adj Close
A3: 40967 | B3: 75.16 | C3: 88.7 | D3: 27.24 | E3: 38.38 | F3: 30.53 | G3: 39.01 | H3: 19.16 | I3: 59.75 | J3: 78.78 | K3: 30.86
A4: 40939 | B4: 73.75 | C4: 81.4 | D4: 26.21 | E4: 38.27 | F4: 29.41 | G4: 39.26 | H4: 18.55 | I4: 57.68 | J4: 74.91 | K4: 27.15
A5: 40907 | B5: 72.92 | C5: 80 | D5: 24.06 | E5: 37.7 | F5: 29.8 | G5: 42.8 | H5: 17.75 | I5: 54.01 | J5: 68.07 | K5: 28.68
A6: 40877 | B6: 68.29 | C6: 77.28 | D6: 24.71 | E6: 35.33 | F6: 28.56 | G6: 43.73 | H6: 15.62 | I6: 53.81 | J6: 75.06 | K6: 25.97
A7: 40847 | B7: 64.99 | C7: 74.09 | D7: 24.13 | E7: 34.09 | F7: 28.89 | G7: 43.29 | H7: 16.4 | I7: 51.72 | J7: 72.95 | K7: 26.35
A8: 40816 | B8: 59.77 | C8: 70.91 | D8: 20.98 | E8: 32.31 | F8: 27.68 | G8: 41.56 | H8: 14.94 | I8: 43.34 | J8: 59.3 | K8: 24.85
A9: 40786 | B9: 66.05 | C9: 72.42 | D9: 19.79 | E9: 32.32 | F9: 27.64 | G9: 42.06 | H9: 15.86 | I9: 47.19 | J9: 77.56 | K9: 28.59
A10: 40753 | B10: 69.14 | C10: 73.17 | D10: 21.75 | E10: 33.32 | F10: 28.4 | G10: 42.42 | H10: 17.42 | I10: 52.03 | J10: 89.44 | K10: 30.98
A11: 40724 | B11: 72.54 | C11: 78.24 | D11: 21.58 | E11: 34.46 | F11: 30.07 | G11: 41.24 | H11: 18.34 | I11: 58.39 | J11: 85.51 | K11: 37.93
A12: 40694 | B12: 76.56 | C12: 75.27 | D12: 21.92 | E12: 35.5 | F12: 30.21 | G12: 40.29 | H12: 18.94 | I12: 58.35 | J12: 84.83 | K12: 41.58
A13: 40662 | B13: 77.87 | C13: 75.84 | D13: 22.37 | E13: 34.73 | F13: 29.79 | G13: 40.09 | H13: 19.72 | I13: 59.66 | J13: 88.56 | K13: 40.74
A14: 40633 | B14: 72.16 | C14: 76.94 | D14: 19.5 | E14: 31.89 | F14: 28.89 | G14: 39.2 | H14: 19.34 | I14: 58.18 | J14: 92.03 | K14: 40.96
... A124: 37287 | B124: 32.96 | C124: 42.35 | D124: 28.68 | E124: 37.6 | F124: 22.34 | G124: 16.98 | H124: 26.57 | I124: 25.98 | J124: 24.84 | K124: 44.51

Sheet _@RISKFitInformation
A1: Created By Version | B1: 5.7.1
A2: Required Version | B2: 5.0.0
A3: Recommended Version | B3: 5.0.0
A4: Modified By Version | B4: 8.2.1
A9: Count | B9: 10
A10: GUID | B10: Name | C10: Range | D10: CRC | E10: Options | F10: Comp. Graph Serialization | G10: PP Graph Serialization | H10: QQ Graph Serialization | I10: Result Display Options
A11: FIT_5824A_7215F | B11: Boeing Cie returns | C11: ='Return rate'!$B$7:$B$127 -> 1.0873348 | D11: 0 | E11: F1 0 0 -1E+300 1E+300 1 0 3 0 1 1 21 BetaGeneral BetaSubj Binomial Expon ExtValue Gamma Geomet IntUniform InvGauss Logistic LogLogistic Lognorm NegBin Normal Pareto Pearson5 Pearson6 Poisson Triang Uniform Weibull 0 1 -1 1 0 1 0 0 0 | F11: GF1_rK0qDwEACACoAQwjACYANwB+AIcAiACUAKAAhgEpAKIBLQD//wAAAAABAQEAAQQAAAAAAAAAAAElRml0IENvbXBhcmlzb24gZm9yIEJvZWluZyBDaWUgcmV0dXJucwEcUmlza0ludmdhdXNzKDEuMDEwMTsxNTAuODU4KQEBBQABAAEDAQEA/wEBAQEBAAEBAQACAAEBAQEBAAEBAQACAAq/AAHNAADeAADzAAAIAQAdAQAyAQBHAQBcAQBxAQAMAAVJbnB1dAAAJQECAA8ACEludkdhdXNzAAEvAQIAEwAMVW51c2VkIEN1cnZlAAJPAQIAEwAMVW51c2VkIEN1cnZlAAOMAQIAEwAMVW51c2VkIEN1cnZlAARMAQIAEwAMVW51c2VkIEN1cnZlAAU5AQIAEwAMVW51c2VkIEN1cnZlAAZOAQIAEwAMVW51c2VkIEN1cnZlAAcjAQIAEwAMVW51c2VkIEN1cnZlAAgpAQIAEwAMVW51c2VkIEN1cnZlAAlgAQIAjgGYAQEBAgGamZmZmZmpPwAAZmZmZmZm7j8AAAUAAQEBAA== | J11: 0 8 | K11: F1 FALSE 1000 0.95 | O11: 4 | P11: FALSE
A12: FIT_93769_87792 | B12: LockheedMartin | C12: ='Return rate'!$C$7:$C$127 -> 0.97914941 | D12: 0 | E12: F1 0 0 -1E+300 1E+300 1 0 3 0 1 1 21 BetaGeneral BetaSubj Binomial Expon ExtValue Gamma Geomet IntUniform InvGauss Logistic LogLogistic Lognorm NegBin Normal Pareto Pearson5 Pearson6 Poisson Triang Uniform Weibull 0 1 -1 1 0 1 0 0 0 | F12: GF1_rK0qDwEACAChAQwjACYANwB4AIEAggCOAJoAfwEpAJsBLQD//wAAAAABAQEAAQQAAAAAAAAAAAEhRml0IENvbXBhcmlzb24gZm9yIExvY2toZWVkTWFydGluARpSaXNrV2VpYnVsbCgxNy44NDY7MS4wMzc2KQEBBQABAAEDAQEA/wEBAQEBAAEBAQACAAEBAQEBAAEBAQACAAq5AAHHAADXAADsAAABAQAWAQArAQBAAQBVAQBqAQAMAAVJbnB1dAAAJQECAA4AB1dlaWJ1bGwAAS8BAgATAAxVbnVzZWQgQ3VydmUAAk8BAgATAAxVbnVzZWQgQ3VydmUAA4wBAgATAAxVbnVzZWQgQ3VydmUABEwBAgATAAxVbnVzZWQgQ3VydmUABTkBAgATAAxVbnVzZWQgQ3VydmUABk4BAgATAAxVbnVzZWQgQ3VydmUAByMBAgATAAxVbnVzZWQgQ3VydmUACCkBAgATAAxVbnVzZWQgQ3VydmUACWABAgCHAZEBAQECAZqZmZmZmak/AABmZmZmZmbuPwAABQABAQEA | J12: 0 8 | K12: F1 FALSE 1000 0.95 | O12: 4 | P12: FALSE
A13: FIT_B75C6_36E6 | B13: IntelCorp | C13: ='Return rate'!$D$7:$D$127 -> 0.90988506 | D13: 0 | E13: F1 0 0 -1E+300 1E+300 1 0 3 0 1 1 21 BetaGeneral BetaSubj Binomial Expon ExtValue Gamma Geomet IntUniform InvGauss Logistic LogLogistic Lognorm NegBin Normal Pareto Pearson5 Pearson6 Poisson Triang Uniform Weibull 0 1 -1 1 0 1 0 0 0 | F13: GF1_rK0qDwEACACbAQwjACYANwB0AH0AfgCKAJYAeQEpAJUBLQD//wAAAAABAQEAAQQAAAAAAAAAAAEcRml0IENvbXBhcmlzb24gZm9yIEludGVsQ29ycAEbUmlza0dhbW1hKDEwNi4wNTswLjAwOTQ3MDIpAQEFAAEAAQMBAQD/AQEBAQEAAQEBAAIAAQEBAQEAAQEBAAIACrUAAcMAANEAAOYAAPsAABABACUBADoBAE8BAGQBAAwABUlucHV0AAAlAQIADAAFR2FtbWEAAS8BAgATAAxVbnVzZWQgQ3VydmUAAk8BAgATAAxVbnVzZWQgQ3VydmUAA4wBAgATAAxVbnVzZWQgQ3VydmUABEwBAgATAAxVbnVzZWQgQ3VydmUABTkBAgATAAxVbnVzZWQgQ3VydmUABk4BAgATAAxVbnVzZWQgQ3VydmUAByMBAgATAAxVbnVzZWQgQ3VydmUACCkBAgATAAxVbnVzZWQgQ3VydmUACWABAgCBAYsBAQECAZqZmZmZmak/AABmZmZmZmbuPwAABQABAQEA | J13: 0 8 | K13: F1 FALSE 1000 0.95 | O13: 4 | P13: FALSE
A14: FIT_EB084_81559 | B14: MerckCie | C14: ='Return rate'!$E$7:$E$127 -> 0.96691817 | D14: 0 | E14: F1 0 0 -1E+300 1E+300 1 0 3 0 1 1 21 BetaGeneral BetaSubj Binomial Expon ExtValue Gamma Geomet IntUniform InvGauss Logistic LogLogistic Lognorm NegBin Normal Pareto Pearson5 Pearson6 Poisson Triang Uniform Weibull 0 1 -1 1 0 1 0 0 0 | F14: GF1_rK0qDwEACACaAQwjACYANwBzAHwAfQCJAJUAeAEpAJQBLQD//wAAAAABAQEAAQQAAAAAAAAAAAEbRml0IENvbXBhcmlzb24gZm9yIE1lcmNrQ2llARtSaXNrR2FtbWEoMTY2LjMzOzAuMDA2MDMxNSkBAQUAAQABAwEBAP8BAQEBAQABAQEAAgABAQEBAQABAQEAAgAKtAABwgAA0AAA5QAA+gAADwEAJAEAOQEATgEAYwEADAAFSW5wdXQAACUBAgAMAAVHYW1tYQABLwECABMADFVudXNlZCBDdXJ2ZQACTwECABMADFVudXNlZCBDdXJ2ZQADjAECABMADFVudXNlZCBDdXJ2ZQAETAECABMADFVudXNlZCBDdXJ2ZQAFOQECABMADFVudXNlZCBDdXJ2ZQAGTgECABMADFVudXNlZCBDdXJ2ZQAHIwECABMADFVudXNlZCBDdXJ2ZQAIKQECABMADFVudXNlZCBDdXJ2ZQAJYAECAIABigEBAQIBmpmZmZmZqT8AAGZmZmZmZu4/AAAFAAEBAQA= | J14: 0 8 | K14: F1 FALSE 1000 0.95 | O14: 4 | P14: FALSE
A15: FIT_52604_94321 | B15: ATT | C15: ='Return rate'!$F$7:$F$127 -> 0.99536577 | D15: 0 | E15: F1 0 0 -1E+300 1E+300 1 0 3 0 1 1 21 BetaGeneral BetaSubj Binomial Expon ExtValue Gamma Geomet IntUniform InvGauss Logistic LogLogistic Lognorm NegBin Normal Pareto Pearson5 Pearson6 Poisson Triang Uniform Weibull 0 1 -1 1 0 1 0 0 0 | F15: GF1_rK0qDwEACACgAQwjACYANwBzAHwAfQCJAJUAfgEpAJoBLQD//wAAAAABAQEAAQQAAAAAAAAAAAEWRml0IENvbXBhcmlzb24gZm9yIEFUVAEgUmlza0xvZ2xvZ2lzdGljKDA7MS4wMDU0OzI3LjQzMykBAQUAAQABAwEBAP8BAQEBAQABAQEAAgABAQEBAQABAQEAAgAKtAABwgAA1gAA6wAAAAEAFQEAKgEAPwEAVAEAaQEADAAFSW5wdXQAACUBAgASAAtMb2dMb2dpc3RpYwABLwECABMADFVudXNlZCBDdXJ2ZQACTwECABMADFVudXNlZCBDdXJ2ZQADjAECABMADFVudXNlZCBDdXJ2ZQAETAECABMADFVudXNlZCBDdXJ2ZQAFOQECABMADFVudXNlZCBDdXJ2ZQAGTgECABMADFVudXNlZCBDdXJ2ZQAHIwECABMADFVudXNlZCBDdXJ2ZQAIKQECABMADFVudXNlZCBDdXJ2ZQAJYAECAIYBkAEBAQIBmpmZmZmZqT8AAGZmZmZmZu4/AAAFAAEBAQA= | J15: 0 8 | K15: F1 FALSE 1000 0.95 | O15: 4 | P15: FALSE
A16: FIT_6AA36_983D2 | B16: Exelon | C16: ='Return rate'!$G$7:$G$127 -> 1.0049888 | D16: 0 | E16: F1 0 0 -1E+300 1E+300 1 0 3 0 1 1 21 BetaGeneral BetaSubj Binomial Expon ExtValue Gamma Geomet IntUniform InvGauss Logistic LogLogistic Lognorm NegBin Normal Pareto Pearson5 Pearson6 Poisson Triang Uniform Weibull 0 1 -1 1 0 1 0 0 0 | F16: GF1_rK0qDwEACACdAQwjACYANwBzAHwAfQCJAJUAewEpAJcBLQD//wAAAAABAQEAAQQAAAAAAAAAAAEZRml0IENvbXBhcmlzb24gZm9yIEV4ZWxvbgEdUmlza0ludmdhdXNzKDEuMDA4MjszODEuODU0NSkBAQUAAQABAwEBAP8BAQEBAQABAQEAAgABAQEBAQABAQEAAgAKtAABwgAA0wAA6AAA/QAAEgEAJwEAPAEAUQEAZgEADAAFSW5wdXQAACUBAgAPAAhJbnZHYXVzcwABLwECABMADFVudXNlZCBDdXJ2ZQACTwECABMADFVudXNlZCBDdXJ2ZQADjAECABMADFVudXNlZCBDdXJ2ZQAETAECABMADFVudXNlZCBDdXJ2ZQAFOQECABMADFVudXNlZCBDdXJ2ZQAGTgECABMADFVudXNlZCBDdXJ2ZQAHIwECABMADFVudXNlZCBDdXJ2ZQAIKQECABMADFVudXNlZCBDdXJ2ZQAJYAECAIMBjQEBAQIBmpmZmZmZqT8AAGZmZmZmZu4/AAAFAAEBAQA= | J16: 0 8 | K16: F1 FALSE 1000 0.95 | O16: 4 | P16: FALSE
A17: FIT_F3F02_6839C | B17: GE | C17: ='Return rate'!$H$7:$H$127 -> 1.0196484 | D17: 0 | E17: F1 0 0 -1E+300 1E+300 1 0 3 0 1 1 21 BetaGeneral BetaSubj Binomial Expon ExtValue Gamma Geomet IntUniform InvGauss Logistic LogLogistic Lognorm NegBin Normal Pareto Pearson5 Pearson6 Poisson Triang Uniform Weibull 0 1 -1 1 0 1 0 0 0 | F17: GF1_rK0qDwEACACYAQwjACYANwBuAHcAeACEAJAAdgEpAJIBLQD//wAAAAABAQEAAQQAAAAAAAAAAAEVRml0IENvbXBhcmlzb24gZm9yIEdFARxSaXNrSW52Z2F1c3MoMS4wMDE7MTMyLjQyMTIpAQEFAAEAAQMBAQD/AQEBAQEAAQEBAAIAAQEBAQEAAQEBAAIACq8AAb0AAM4AAOMAAPgAAA0BACIBADcBAEwBAGEBAAwABUlucHV0AAAlAQIADwAISW52R2F1c3MAAS8BAgATAAxVbnVzZWQgQ3VydmUAAk8BAgATAAxVbnVzZWQgQ3VydmUAA4wBAgATAAxVbnVzZWQgQ3VydmUABEwBAgATAAxVbnVzZWQgQ3VydmUABTkBAgATAAxVbnVzZWQgQ3VydmUABk4BAgATAAxVbnVzZWQgQ3VydmUAByMBAgATAAxVbnVzZWQgQ3VydmUACCkBAgATAAxVbnVzZWQgQ3VydmUACWABAgB+AYgBAQECAZqZmZmZmak/AABmZmZmZmbuPwAABQABAQEA | J17: 0 8 | K17: F1 FALSE 1000 0.95 | O17: 4 | P17: FALSE
A18: FIT_13995_DEBDD | B18: Honeywell | C18: ='Return rate'!$I$7:$I$127 -> 1.0311946 | D18: 0 | E18: F1 0 0 -1E+300 1E+300 1 0 3 0 1 1 21 BetaGeneral BetaSubj Binomial Expon ExtValue Gamma Geomet IntUniform InvGauss Logistic LogLogistic Lognorm NegBin Normal Pareto Pearson5 Pearson6 Poisson Triang Uniform Weibull 0 1 -1 1 0 1 0 0 0 | F18: GF1_rK0qDwEACACgAQwjACYANwB2AH8AgACMAJgAfgEpAJoBLQD//wAAAAABAQEAAQQAAAAAAAAAAAEcRml0IENvbXBhcmlzb24gZm9yIEhvbmV5d2VsbAEdUmlza0ludmdhdXNzKDEuMDEwMjsxNTEuMTcwNikBAQUAAQABAwEBAP8BAQEBAQABAQEAAgABAQEBAQABAQEAAgAKtwABxQAA1gAA6wAAAAEAFQEAKgEAPwEAVAEAaQEADAAFSW5wdXQAACUBAgAPAAhJbnZHYXVzcwABLwECABMADFVudXNlZCBDdXJ2ZQACTwECABMADFVudXNlZCBDdXJ2ZQADjAECABMADFVudXNlZCBDdXJ2ZQAETAECABMADFVudXNlZCBDdXJ2ZQAFOQECABMADFVudXNlZCBDdXJ2ZQAGTgECABMADFVudXNlZCBDdXJ2ZQAHIwECABMADFVudXNlZCBDdXJ2ZQAIKQECABMADFVudXNlZCBDdXJ2ZQAJYAECAIYBkAEBAQIBmpmZmZmZqT8AAGZmZmZmZu4/AAAFAAEBAQA= | J18: 0 8 | K18: F1 FALSE 1000 0.95 | O18: 4 | P18: FALSE
A19: FIT_6C5C3_CFCF9 | B19: Schlumberger | C19: ='Return rate'!$J$7:$J$127 -> 1.0526436 | D19: 0 | E19: F1 0 0 -1E+300 1E+300 1 0 3 0 1 1 21 BetaGeneral BetaSubj Binomial Expon ExtValue Gamma Geomet IntUniform InvGauss Logistic LogLogistic Lognorm NegBin Normal Pareto Pearson5 Pearson6 Poisson Triang Uniform Weibull 0 1 -1 1 0 1 0 0 0 | F19: GF1_rK0qDwEACACdAQwjACYANwB2AH8AgACMAJgAewEpAJcBLQD//wAAAAABAQEAAQQAAAAAAAAAAAEfRml0IENvbXBhcmlzb24gZm9yIFNjaGx1bWJlcmdlcgEaUmlza0dhbW1hKDEwNS42ODswLjAwOTU5OSkBAQUAAQABAwEBAP8BAQEBAQABAQEAAgABAQEBAQABAQEAAgAKtwABxQAA0wAA6AAA/QAAEgEAJwEAPAEAUQEAZgEADAAFSW5wdXQAACUBAgAMAAVHYW1tYQABLwECABMADFVudXNlZCBDdXJ2ZQACTwECABMADFVudXNlZCBDdXJ2ZQADjAECABMADFVudXNlZCBDdXJ2ZQAETAECABMADFVudXNlZCBDdXJ2ZQAFOQECABMADFVudXNlZCBDdXJ2ZQAGTgECABMADFVudXNlZCBDdXJ2ZQAHIwECABMADFVudXNlZCBDdXJ2ZQAIKQECABMADFVudXNlZCBDdXJ2ZQAJYAECAIMBjQEBAQIBmpmZmZmZqT8AAGZmZmZmZu4/AAAFAAEBAQA= | J19: 0 8 | K19: F1 FALSE 1000 0.95 | O19: 4 | P19: FALSE
A20: FIT_315F9_EC88B | B20: Avery | C20: ='Return rate'!$K$7:$K$127 -> 0.99391283 | D20: 0 | E20: F1 0 0 -1E+300 1E+300 1 0 3 0 1 1 21 BetaGeneral BetaSubj Binomial Expon ExtValue Gamma Geomet IntUniform InvGauss Logistic LogLogistic Lognorm NegBin Normal Pareto Pearson5 Pearson6 Poisson Triang Uniform Weibull 0 1 -1 1 0 1 0 0 0 | F20: GF1_rK0qDwEACACcAQwjACYANwByAHsAfACIAJQAegEpAJYBLQD//wAAAAABAQEAAQQAAAAAAAAAAAEYRml0IENvbXBhcmlzb24gZm9yIEF2ZXJ5AR1SaXNrSW52Z2F1c3MoMS4wMDAzOzE0Ni41ODU3KQEBBQABAAEDAQEA/wEBAQEBAAEBAQACAAEBAQEBAAEBAQACAAqzAAHBAADSAADnAAD8AAARAQAmAQA7AQBQAQBlAQAMAAVJbnB1dAAAJQECAA8ACEludkdhdXNzAAEvAQIAEwAMVW51c2VkIEN1cnZlAAJPAQIAEwAMVW51c2VkIEN1cnZlAAOMAQIAEwAMVW51c2VkIEN1cnZlAARMAQIAEwAMVW51c2VkIEN1cnZlAAU5AQIAEwAMVW51c2VkIEN1cnZlAAZOAQIAEwAMVW51c2VkIEN1cnZlAAcjAQIAEwAMVW51c2VkIEN1cnZlAAgpAQIAEwAMVW51c2VkIEN1cnZlAAlgAQIAggGMAQEBAgGamZmZmZmpPwAAZmZmZmZm7j8AAAUAAQEBAA== | J20: 0 8 | K20: F1 FALSE 1000 0.95 | O20: 4 | P20: FALSE

Sheet Return rate
B1: Boeing Cie | C1: Lockheed Martin | D1: Intel Corp. | E1: Merck & Company | F1: AT&T | G1: Exelon | H1: GE | I1: Honeywell | J1: Schlumberger | K1: Avery
A2: Best fit | B2: =_xll.RiskLognorm(1.0102,0.08265,_xll.RiskName("Boeing Cie returns")) -> 1.0102 | C2: =_xll.RiskLognorm(1.0084,0.067323,_xll.RiskName("LockheedMartin")) -> 1.0084 | D2: =_xll.RiskLognorm(1.0044,0.099085,_xll.RiskName("IntelCorp")) -> 1.0044 | E2: =_xll.RiskLognorm(1.0032,0.078483,_xll.RiskName("MerckCie")) -> 1.0032 | F2: =_xll.RiskLognorm(1.0049,0.068432,_xll.RiskName("ATT")) -> 1.0049 | G2: =_xll.RiskLognorm(1.0082,0.051797,_xll.RiskName("Exelon")) -> 1.0082 | H2: =_xll.RiskLognorm(1.0011,0.086978,_xll.RiskName("GE")) -> 1.0011 | I2: =_xll.RiskLognorm(1.0103,0.082517,_xll.RiskName("Honeywell")) -> 1.0103 | J2: =_xll.RiskLognorm(1.0145,0.10039,_xll.RiskName("Schlumberger")) -> 1.0145 | K2: =_xll.RiskLognorm(1.0004,0.082606,_xll.RiskName("Avery")) -> 1.0004
A3: mean | B3: =_xll.RiskTheoMean(B2) -> 1.0102 | C3: =_xll.RiskTheoMean(C2) -> 1.0084 | D3: =_xll.RiskTheoMean(D2) -> 1.0044 | E3: =_xll.RiskTheoMean(E2) -> 1.0032 | F3: =_xll.RiskTheoMean(F2) -> 1.0049 | G3: =_xll.RiskTheoMean(G2) -> 1.0082 | H3: =_xll.RiskTheoMean(H2) -> 1.0011 | I3: =_xll.RiskTheoMean(I2) -> 1.0103 | ... K3: =_xll.RiskTheoMean(K2) -> 1.0004
A4: std dev | B4: =_xll.RiskTheoStdDev(B2) -> 0.08265 | C4: =_xll.RiskTheoStdDev(C2) -> 0.067323 | D4: =_xll.RiskTheoStdDev(D2) -> 0.099085 | E4: =_xll.RiskTheoStdDev(E2) -> 0.078483 | F4: =_xll.RiskTheoStdDev(F2) -> 0.068432 | G4: =_xll.RiskTheoStdDev(G2) -> 0.051797 | H4: =_xll.RiskTheoStdDev(H2) -> 0.086978 | I4: =_xll.RiskTheoStdDev(I2) -> 0.082517 | ... K4: =_xll.RiskTheoStdDev(K2) -> 0.082606
A6: Date | B6: Returns | C6: Returns | D6: Returns | E6: Returns | F6: Returns | G6: Returns | H6: Returns | I6: Returns | J6: Returns | K6: Returns | N6: Correlations | O6: =B1 -> Boeing Cie | P6: =C1 -> Lockheed Martin | Q6: =D1 -> Intel Corp. | R6: =E1 -> Merck & Company | S6: =F1 -> AT&T | T6: =G1 -> Exelon | U6: =H1 -> GE | V6: =I1 -> Honeywell | ... X6: =K1 -> Avery
A7: 40967 | B7: ='Adjusted close'!B3/'Adjusted close'!B4 -> 1.0191186 | C7: ='Adjusted close'!C3/'Adjusted close'!C4 -> 1.0896806 | D7: ='Adjusted close'!D3/'Adjusted close'!D4 -> 1.039298 | E7: ='Adjusted close'!E3/'Adjusted close'!E4 -> 1.0028743 | F7: ='Adjusted close'!F3/'Adjusted close'!F4 -> 1.0380823 | G7: ='Adjusted close'!G3/'Adjusted close'!G4 -> 0.9936322 | H7: ='Adjusted close'!H3/'Adjusted close'!H4 -> 1.0328841 | I7: ='Adjusted close'!I3/'Adjusted close'!I4 -> 1.0358877 | ... K7: ='Adjusted close'!K3/'Adjusted close'!K4 -> 1.1366483 | N7: {=TRANSPOSE(O6:X6)} -> Boeing Cie | O7: 1 | P7: =CORREL($B$7:$B$127,C$7:C$127) -> 0.54422797 | Q7: =CORREL($B$7:$B$127,D$7:D$127) -> 0.28657911 | R7: =CORREL($B$7:$B$127,E$7:E$127) -> 0.30200694 | S7: =CORREL($B$7:$B$127,F$7:F$127) -> 0.28462589 | T7: =CORREL($B$7:$B$127,G$7:G$127) -> 0.23060767 | U7: =CORREL($B$7:$B$127,H$7:H$127) -> 0.53729598 | V7: =CORREL($B$7:$B$127,I$7:I$127) -> 0.63826973 | W7: =CORREL($B$7:$B$127,J$7:J$127) -> 0.41388878 | X7: =CORREL($B$7:$B$127,K$7:K$127) -> 0.42258748
A8: 40939 | B8: ='Adjusted close'!B4/'Adjusted close'!B5 -> 1.0113823 | C8: ='Adjusted close'!C4/'Adjusted close'!C5 -> 1.0175 | D8: ='Adjusted close'!D4/'Adjusted close'!D5 -> 1.0893599 | E8: ='Adjusted close'!E4/'Adjusted close'!E5 -> 1.0151194 | F8: ='Adjusted close'!F4/'Adjusted close'!F5 -> 0.98691275 | G8: ='Adjusted close'!G4/'Adjusted close'!G5 -> 0.91728972 | H8: ='Adjusted close'!H4/'Adjusted close'!H5 -> 1.0450704 | I8: ='Adjusted close'!I4/'Adjusted close'!I5 -> 1.0679504 | ... K8: ='Adjusted close'!K4/'Adjusted close'!K5 -> 0.94665272 | N8: Lockheed Martin | O8: =$P$7 -> 0.54422797 | P8: 1 | Q8: =CORREL($C$7:$C$127,D$7:D$127) -> -0.02511338 | R8: =CORREL($C$7:$C$127,E$7:E$127) -> 0.1171669 | S8: =CORREL($C$7:$C$127,F$7:F$127) -> 0.08103626 | T8: =CORREL($C$7:$C$127,G$7:G$127) -> 0.21057305 | U8: =CORREL($C$7:$C$127,H$7:H$127) -> 0.41028154 | V8: =CORREL($C$7:$C$127,I$7:I$127) -> 0.41609217 | W8: =CORREL($C$7:$C$127,J$7:J$127) -> 0.20967325 | X8: =CORREL($C$7:$C$127,K$7:K$127) -> 0.41178439
A9: 40907 | B9: ='Adjusted close'!B5/'Adjusted close'!B6 -> 1.0677991 | C9: ='Adjusted close'!C5/'Adjusted close'!C6 -> 1.0351967 | D9: ='Adjusted close'!D5/'Adjusted close'!D6 -> 0.97369486 | E9: ='Adjusted close'!E5/'Adjusted close'!E6 -> 1.0670818 | F9: ='Adjusted close'!F5/'Adjusted close'!F6 -> 1.0434174 | G9: ='Adjusted close'!G5/'Adjusted close'!G6 -> 0.97873314 | H9: ='Adjusted close'!H5/'Adjusted close'!H6 -> 1.1363636 | I9: ='Adjusted close'!I5/'Adjusted close'!I6 -> 1.0037168 | ... K9: ='Adjusted close'!K5/'Adjusted close'!K6 -> 1.1043512 | N9: Intel Corp. | O9: =$Q$7 -> 0.28657911 | P9: =$Q$8 -> -0.02511338 | Q9: 1 | R9: =CORREL($D$7:$D$127,E$7:E$127) -> 0.28938439 | S9: =CORREL($D$7:$D$127,F$7:F$127) -> 0.40040852 | T9: =CORREL($D$7:$D$127,G$7:G$127) -> 0.15222593 | U9: =CORREL($D$7:$D$127,H$7:H$127) -> 0.41975547 | V9: =CORREL($D$7:$D$127,I$7:I$127) -> 0.52654022 | W9: =CORREL($D$7:$D$127,J$7:J$127) -> 0.30023704 | X9: =CORREL($D$7:$D$127,K$7:K$127) -> 0.29434426
A10: 40877 | B10: ='Adjusted close'!B6/'Adjusted close'!B7 -> 1.050777 | C10: ='Adjusted close'!C6/'Adjusted close'!C7 -> 1.0430557 | D10: ='Adjusted close'!D6/'Adjusted close'!D7 -> 1.0240365 | E10: ='Adjusted close'!E6/'Adjusted close'!E7 -> 1.0363743 | F10: ='Adjusted close'!F6/'Adjusted close'!F7 -> 0.98857736 | G10: ='Adjusted close'!G6/'Adjusted close'!G7 -> 1.010164 | H10: ='Adjusted close'!H6/'Adjusted close'!H7 -> 0.95243902 | I10: ='Adjusted close'!I6/'Adjusted close'!I7 -> 1.0404099 | ... K10: ='Adjusted close'!K6/'Adjusted close'!K7 -> 0.98557875 | N10: Merck & Company | O10: =$R$7 -> 0.30200694 | P10: =$R$8 -> 0.1171669 | Q10: =$R$9 -> 0.28938439 | R10: 1 | S10: =CORREL($E$7:$E$127,F$7:F$127) -> 0.40921193 | T10: =CORREL($E$7:$E$127,G$7:G$127) -> 0.28282268 | U10: =CORREL($E$7:$E$127,H$7:H$127) -> 0.27292062 | V10: =CORREL($E$7:$E$127,I$7:I$127) -> 0.36352954 | W10: =CORREL($E$7:$E$127,J$7:J$127) -> 0.17359778 | X10: =CORREL($E$7:$E$127,K$7:K$127) -> 0.20816504
A11: 40847 | B11: ='Adjusted close'!B7/'Adjusted close'!B8 -> 1.0873348 | C11: ='Adjusted close'!C7/'Adjusted close'!C8 -> 1.0448456 | D11: ='Adjusted close'!D7/'Adjusted close'!D8 -> 1.150143 | E11: ='Adjusted close'!E7/'Adjusted close'!E8 -> 1.0550913 | F11: ='Adjusted close'!F7/'Adjusted close'!F8 -> 1.0437139 | G11: ='Adjusted close'!G7/'Adjusted close'!G8 -> 1.0416266 | H11: ='Adjusted close'!H7/'Adjusted close'!H8 -> 1.0977242 | I11: ='Adjusted close'!I7/'Adjusted close'!I8 -> 1.1933549 | ... K11: ='Adjusted close'!K7/'Adjusted close'!K8 -> 1.0603622 | N11: AT&T | O11: =$S$7 -> 0.28462589 | P11: =$S$8 -> 0.08103626 | Q11: =$S$9 -> 0.40040852 | R11: =$S$10 -> 0.40921193 | S11: 1 | T11: =CORREL($F$7:$F$127,G$7:G$127) -> 0.38804349 | U11: =CORREL($F$7:$F$127,H$7:H$127) -> 0.40953616 | V11: =CORREL($F$7:$F$127,I$7:I$127) -> 0.54724718 | W11: =CORREL($F$7:$F$127,J$7:J$127) -> 0.28173963 | X11: =CORREL($F$7:$F$127,K$7:K$127) -> 0.37569149
A12: 40816 | B12: ='Adjusted close'!B8/'Adjusted close'!B9 -> 0.90492051 | C12: ='Adjusted close'!C8/'Adjusted close'!C9 -> 0.97914941 | D12: ='Adjusted close'!D8/'Adjusted close'!D9 -> 1.0601314 | E12: ='Adjusted close'!E8/'Adjusted close'!E9 -> 0.99969059 | F12: ='Adjusted close'!F8/'Adjusted close'!F9 -> 1.0014472 | G12: ='Adjusted close'!G8/'Adjusted close'!G9 -> 0.98811222 | H12: ='Adjusted close'!H8/'Adjusted close'!H9 -> 0.94199243 | I12: ='Adjusted close'!I8/'Adjusted close'!I9 -> 0.91841492 | ... K12: ='Adjusted close'!K8/'Adjusted close'!K9 -> 0.86918503 | N12: Exelon | O12: =$T$7 -> 0.23060767 | P12: =$T$8 -> 0.21057305 | Q12: =$T$9 -> 0.15222593 | R12: =$T$10 -> 0.28282268 | S12: =$T$11 -> 0.38804349 | T12: 1 | U12: =CORREL($G$7:$G$127,H$7:H$127) -> 0.22926614 | V12: =CORREL($G$7:$G$127,I$7:I$127) -> 0.33319458 | W12: =CORREL($G$7:$G$127,J$7:J$127) -> 0.37272715 | X12: =CORREL($G$7:$G$127,K$7:K$127) -> 0.15527982
A13: 40786 | B13: ='Adjusted close'!B9/'Adjusted close'!B10 -> 0.95530807 | C13: ='Adjusted close'!C9/'Adjusted close'!C10 -> 0.9897499 | D13: ='Adjusted close'!D9/'Adjusted close'!D10 -> 0.90988506 | E13: ='Adjusted close'!E9/'Adjusted close'!E10 -> 0.969988 | F13: ='Adjusted close'!F9/'Adjusted close'!F10 -> 0.97323944 | G13: ='Adjusted close'!G9/'Adjusted close'!G10 -> 0.99151344 | H13: ='Adjusted close'!H9/'Adjusted close'!H10 -> 0.91044776 | I13: ='Adjusted close'!I9/'Adjusted close'!I10 -> 0.90697674 | ... K13: ='Adjusted close'!K9/'Adjusted close'!K10 -> 0.92285345 | N13: GE | O13: =$U$7 -> 0.53729598 | P13: =$U$8 -> 0.41028154 | Q13: =$U$9 -> 0.41975547 | R13: =$U$10 -> 0.27292062 | S13: =$U$11 -> 0.40953616 | T13: =$U$12 -> 0.22926614 | U13: 1 | V13: =CORREL($H$7:$H$127,I$7:I$127) -> 0.59749589 | W13: =CORREL($H$7:$H$127,J$7:J$127) -> 0.41692441 | X13: =CORREL($H$7:$H$127,K$7:K$127) -> 0.60975618
A14: 40753 | B14: ='Adjusted close'!B10/'Adjusted close'!B11 -> 0.95312931 | C14: ='Adjusted close'!C10/'Adjusted close'!C11 -> 0.93519939 | D14: ='Adjusted close'!D10/'Adjusted close'!D11 -> 1.0078777 | E14: ='Adjusted close'!E10/'Adjusted close'!E11 -> 0.96691817 | F14: ='Adjusted close'!F10/'Adjusted close'!F11 -> 0.94446292 | G14: ='Adjusted close'!G10/'Adjusted close'!G11 -> 1.028613 | H14: ='Adjusted close'!H10/'Adjusted close'!H11 -> 0.94983642 | I14: ='Adjusted close'!I10/'Adjusted close'!I11 -> 0.89107724 | ... K14: ='Adjusted close'!K10/'Adjusted close'!K11 -> 0.81676773 | N14: Honeywell | O14: =$V$7 -> 0.63826973 | P14: =$V$8 -> 0.41609217 | Q14: =$V$9 -> 0.52654022 | R14: =$V$10 -> 0.36352954 | S14: =$V$11 -> 0.54724718 | T14: =$V$12 -> 0.33319458 | U14: =$V$13 -> 0.59749589 | V14: 1 | W14: =CORREL($I$7:$I$127,J$7:J$127) -> 0.53622268 | X14: =CORREL($I$7:$I$127,K$7:K$127) -> 0.56777129
A15: 40724 | B15: ='Adjusted close'!B11/'Adjusted close'!B12 -> 0.94749216 | C15: ='Adjusted close'!C11/'Adjusted close'!C12 -> 1.039458 | D15: ='Adjusted close'!D11/'Adjusted close'!D12 -> 0.98448905 | E15: ='Adjusted close'!E11/'Adjusted close'!E12 -> 0.97070423 | F15: ='Adjusted close'!F11/'Adjusted close'!F12 -> 0.99536577 | G15: ='Adjusted close'!G11/'Adjusted close'!G12 -> 1.0235791 | H15: ='Adjusted close'!H11/'Adjusted close'!H12 -> 0.96832101 | I15: ='Adjusted close'!I11/'Adjusted close'!I12 -> 1.0006855 | ... K15: ='Adjusted close'!K11/'Adjusted close'!K12 -> 0.91221741 | N15: Schlumberger | O15: =$W$7 -> 0.41388878 | P15: =$W$8 -> 0.20967325 | Q15: =$W$9 -> 0.30023704 | R15: =$W$10 -> 0.17359778 | S15: =$W$11 -> 0.28173963 | T15: =$W$12 -> 0.37272715 | U15: =$W$13 -> 0.41692441 | V15: =$W$14 -> 0.53622268 | W15: 1 | X15: =CORREL($J$7:$J$127,K$7:K$127) -> 0.40604701
A16: 40694 | B16: ='Adjusted close'!B12/'Adjusted close'!B13 -> 0.98317709 | C16: ='Adjusted close'!C12/'Adjusted close'!C13 -> 0.99248418 | D16: ='Adjusted close'!D12/'Adjusted close'!D13 -> 0.97988377 | E16: ='Adjusted close'!E12/'Adjusted close'!E13 -> 1.022171 | F16: ='Adjusted close'!F12/'Adjusted close'!F13 -> 1.0140987 | G16: ='Adjusted close'!G12/'Adjusted close'!G13 -> 1.0049888 | H16: ='Adjusted close'!H12/'Adjusted close'!H13 -> 0.96044625 | I16: ='Adjusted close'!I12/'Adjusted close'!I13 -> 0.97804224 | ... K16: ='Adjusted close'!K12/'Adjusted close'!K13 -> 1.0206186 | N16: Avery | O16: =$X$7 -> 0.42258748 | P16: =$X$8 -> 0.41178439 | Q16: =$X$9 -> 0.29434426 | R16: =$X$10 -> 0.20816504 | S16: =$X$11 -> 0.37569149 | T16: =$X$12 -> 0.15527982 | U16: =$X$13 -> 0.60975618 | V16: =$X$14 -> 0.56777129 | W16: =$X$15 -> 0.40604701 | X16: 1
A17: 40662 | B17: ='Adjusted close'!B13/'Adjusted close'!B14 -> 1.0791297 | C17: ='Adjusted close'!C13/'Adjusted close'!C14 -> 0.98570315 | D17: ='Adjusted close'!D13/'Adjusted close'!D14 -> 1.1471795 | E17: ='Adjusted close'!E13/'Adjusted close'!E14 -> 1.0890561 | F17: ='Adjusted close'!F13/'Adjusted close'!F14 -> 1.0311526 | G17: ='Adjusted close'!G13/'Adjusted close'!G14 -> 1.0227041 | H17: ='Adjusted close'!H13/'Adjusted close'!H14 -> 1.0196484 | I17: ='Adjusted close'!I13/'Adjusted close'!I14 -> 1.0254383 | ... K17: ='Adjusted close'!K13/'Adjusted close'!K14 -> 0.99462891
A18: 40633 | B18: ='Adjusted close'!B14/'Adjusted close'!B15 -> 1.0267501 | C18: ='Adjusted close'!C14/'Adjusted close'!C15 -> 1.0157096 | D18: ='Adjusted close'!D14/'Adjusted close'!D15 -> 0.93975904 | E18: ='Adjusted close'!E14/'Adjusted close'!E15 -> 1.0254019 | F18: ='Adjusted close'!F14/'Adjusted close'!F15 -> 1.0783875 | G18: ='Adjusted close'!G14/'Adjusted close'!G15 -> 0.98740554 | H18: ='Adjusted close'!H14/'Adjusted close'!H15 -> 0.95837463 | I18: ='Adjusted close'!I14/'Adjusted close'!I15 -> 1.0311946 | ... K18: ='Adjusted close'!K14/'Adjusted close'!K15 -> 1.0510649 | N18: No correlation
A19: 40602 | B19: ='Adjusted close'!B15/'Adjusted close'!B16 -> 1.0424206 | C19: ='Adjusted close'!C15/'Adjusted close'!C16 -> 1.0038431 | D19: ='Adjusted close'!D15/'Adjusted close'!D16 -> 1.0092412 | E19: ='Adjusted close'!E15/'Adjusted close'!E16 -> 0.98200189 | F19: ='Adjusted close'!F15/'Adjusted close'!F16 -> 1.0311778 | G19: ='Adjusted close'!G15/'Adjusted close'!G16 -> 0.99448898 | H19: ='Adjusted close'!H15/'Adjusted close'!H16 -> 1.0461379 | I19: ='Adjusted close'!I15/'Adjusted close'!I16 -> 1.04 | ... K19: ='Adjusted close'!K15/'Adjusted close'!K16 -> 0.95467908 | O19: 1 | P19: 0 | Q19: 0 | R19: 0 | S19: 0 | T19: 0 | U19: 0 | V19: 0 | W19: 0 | X19: 0
A20: 40574 | B20: ='Adjusted close'!B16/'Adjusted close'!B17 -> 1.0645823 | C20: ='Adjusted close'!C16/'Adjusted close'!C17 -> 1.1386751 | D20: ='Adjusted close'!D16/'Adjusted close'!D17 -> 1.0203474 | E20: ='Adjusted close'!E16/'Adjusted close'!E17 -> 0.92037198 | F20: ='Adjusted close'!F16/'Adjusted close'!F17 -> 0.95025604 | G20: ='Adjusted close'!G16/'Adjusted close'!G17 -> 1.0209719 | H20: ='Adjusted close'!H16/'Adjusted close'!H17 -> 1.1010274 | I20: ='Adjusted close'!I16/'Adjusted close'!I17 -> 1.0536026 | ... K20: ='Adjusted close'!K16/'Adjusted close'!K17 -> 0.99391283 | O20: 0 | P20: 1 | Q20: 0 | R20: 0 | S20: 0 | T20: 0 | U20: 0 | V20: 0 | W20: 0 | X20: 0
A21: 40543 | B21: ='Adjusted close'!B17/'Adjusted close'!B18 -> 1.0234324 | C21: ='Adjusted close'!C17/'Adjusted close'!C18 -> 1.0274419 | D21: ='Adjusted close'!D17/'Adjusted close'!D18 -> 0.99407992 | E21: ='Adjusted close'!E17/'Adjusted close'!E18 -> 1.0568182 | F21: ='Adjusted close'!F17/'Adjusted close'!F18 -> 1.0572312 | G21: ='Adjusted close'!G17/'Adjusted close'!G18 -> 1.0576143 | H21: ='Adjusted close'!H17/'Adjusted close'!H18 -> 1.1648936 | I21: ='Adjusted close'!I17/'Adjusted close'!I18 -> 1.0693666 | ... K21: ='Adjusted close'!K17/'Adjusted close'!K18 -> 1.1279868 | O21: 0 | P21: 0 | Q21: 1 | R21: 0 | S21: 0 | T21: 0 | U21: 0 | V21: 0 | W21: 0 | X21: 0
A22: 40512 | B22: ='Adjusted close'!B18/'Adjusted close'!B19 -> 0.90813032 | C22: ='Adjusted close'!C18/'Adjusted close'!C19 -> 0.96484667 | D22: ='Adjusted close'!D18/'Adjusted close'!D19 -> 1.0634837 | E22: ='Adjusted close'!E18/'Adjusted close'!E19 -> 0.94927114 | F22: ='Adjusted close'!F18/'Adjusted close'!F19 -> 0.9743783 | G22: ='Adjusted close'!G18/'Adjusted close'!G19 -> 0.97675033 | H22: ='Adjusted close'!H18/'Adjusted close'!H19 -> 0.98817346 | I22: ='Adjusted close'!I18/'Adjusted close'!I19 -> 1.061742 | ... K22: ='Adjusted close'!K18/'Adjusted close'!K19 -> 1.0382093 | O22: 0 | P22: 0 | Q22: 0 | R22: 1 | S22: 0 | T22: 0 | U22: 0 | V22: 0 | W22: 0 | X22: 0
A23: 40480 | B23: ='Adjusted close'!B19/'Adjusted close'!B20 -> 1.0617015 | C23: ='Adjusted close'!C19/'Adjusted close'!C20 -> 1.0001496 | D23: ='Adjusted close'!D19/'Adjusted close'!D20 -> 1.0443836 | E23: ='Adjusted close'!E19/'Adjusted close'!E20 -> 0.9864826 | F23: ='Adjusted close'!F19/'Adjusted close'!F20 -> 1.0118185 | G23: ='Adjusted close'!G19/'Adjusted close'!G20 -> 0.95871327 | H23: ='Adjusted close'!H19/'Adjusted close'!H20 -> 0.9857513 | I23: ='Adjusted close'!I19/'Adjusted close'!I20 -> 1.072104 | ... K23: ='Adjusted close'!K19/'Adjusted close'!K20 -> 0.97933538 | O23: 0 | P23: 0 | Q23: 0 | R23: 0 | S23: 1 | T23: 0 | U23: 0 | V23: 0 | W23: 0 | X23: 0
A24: 40451 | B24: ='Adjusted close'!B20/'Adjusted close'!B21 -> 1.0885346 | C24: ='Adjusted close'!C20/'Adjusted close'!C21 -> 1.0253106 | D24: ='Adjusted close'!D20/'Adjusted close'!D21 -> 1.0863095 | E24: ='Adjusted close'!E20/'Adjusted close'!E21 -> 1.0578035 | F24: ='Adjusted close'!F20/'Adjusted close'!F21 -> 1.0580879 | G24: ='Adjusted close'!G20/'Adjusted close'!G21 -> 1.0455508 | H24: ='Adjusted close'!H20/'Adjusted close'!H21 -> 1.1303075 | I24: ='Adjusted close'!I20/'Adjusted close'!I21 -> 1.125 | ... K24: ='Adjusted close'!K20/'Adjusted close'!K21 -> 1.1411727 | O24: 0 | P24: 0 | Q24: 0 | R24: 0 | S24: 0 | T24: 1 | U24: 0 | V24: 0 | W24: 0 | X24: 0
A25: 40421 | B25: ='Adjusted close'!B21/'Adjusted close'!B22 -> 0.90249503 | C25: ='Adjusted close'!C21/'Adjusted close'!C22 -> 0.93328561 | D25: ='Adjusted close'!D21/'Adjusted close'!D22 -> 0.86419753 | E25: ='Adjusted close'!E21/'Adjusted close'!E22 -> 1.0201738 | F25: ='Adjusted close'!F21/'Adjusted close'!F22 -> 1.0420345 | G25: ='Adjusted close'!G21/'Adjusted close'!G22 -> 0.98590078 | H25: ='Adjusted close'!H21/'Adjusted close'!H22 -> 0.89809336 | I25: ='Adjusted close'!I21/'Adjusted close'!I22 -> 0.91796875 | ... K25: ='Adjusted close'!K21/'Adjusted close'!K22 -> 0.91273997 | O25: 0 | P25: 0 | Q25: 0 | R25: 0 | S25: 0 | T25: 0 | U25: 1 | V25: 0 | W25: 0 | X25: 0
A26: 40389 | B26: ='Adjusted close'!B22/'Adjusted close'!B23 -> 1.0859375 | C26: ='Adjusted close'!C22/'Adjusted close'!C23 -> 1.0086643 | D26: ='Adjusted close'!D22/'Adjusted close'!D23 -> 1.0594005 | E26: ='Adjusted close'!E22/'Adjusted close'!E23 -> 0.98562251 | F26: ='Adjusted close'!F22/'Adjusted close'!F23 -> 1.0912844 | G26: ='Adjusted close'!G22/'Adjusted close'!G23 -> 1.1015243 | H26: ='Adjusted close'!H22/'Adjusted close'!H23 -> 1.1183824 | I26: ='Adjusted close'!I22/'Adjusted close'!I23 -> 1.0981233 | ... K26: ='Adjusted close'!K22/'Adjusted close'!K23 -> 1.1158715 | O26: 0 | P26: 0 | Q26: 0 | R26: 0 | S26: 0 | T26: 0 | U26: 0 | V26: 1 | W26: 0 | X26: 0
A27: 40359 | B27: ='Adjusted close'!B23/'Adjusted close'!B24 -> 0.97773444 | C27: ='Adjusted close'!C23/'Adjusted close'!C24 -> 0.93228325 | D27: ='Adjusted close'!D23/'Adjusted close'!D24 -> 0.90796635 | E27: ='Adjusted close'!E23/'Adjusted close'!E24 -> 1.0494382 | F27: ='Adjusted close'!F23/'Adjusted close'!F24 -> 0.99543379 | G27: ='Adjusted close'!G23/'Adjusted close'!G24 -> 0.98387097 | H27: ='Adjusted close'!H23/'Adjusted close'!H24 -> 0.88714938 | I27: ='Adjusted close'!I23/'Adjusted close'!I24 -> 0.91242661 | ... K27: ='Adjusted close'!K23/'Adjusted close'!K24 -> 0.93990238 | O27: 0 | P27: 0 | Q27: 0 | R27: 0 | S27: 0 | T27: 0 | U27: 0 | V27: 0 | W27: 1 | X27: 0
A28: 40326 | B28: ='Adjusted close'!B24/'Adjusted close'!B25 -> 0.89122248 | C28: ='Adjusted close'!C24/'Adjusted close'!C25 -> 0.94890138 | D28: ='Adjusted close'!D24/'Adjusted close'!D25 -> 0.94439252 | E28: ='Adjusted close'!E24/'Adjusted close'!E25 -> 0.96141975 | F28: ='Adjusted close'!F24/'Adjusted close'!F25 -> 0.93231162 | G28: ='Adjusted close'!G24/'Adjusted close'!G25 -> 0.89649924 | H28: ='Adjusted close'!H24/'Adjusted close'!H25 -> 0.86708145 | I28: ='Adjusted close'!I24/'Adjusted close'!I25 -> 0.9072348 | ... K28: ='Adjusted close'!K24/'Adjusted close'!K25 -> 0.88094598 | O28: 0 | P28: 0 | Q28: 0 | R28: 0 | S28: 0 | T28: 0 | U28: 0 | V28: 0 | W28: 0 | X28: 1
A29: 40298 | B29: ='Adjusted close'!B25/'Adjusted close'!B26 -> 0.99754371 | C29: ='Adjusted close'!C25/'Adjusted close'!C26 -> 1.0200678 | D29: ='Adjusted close'!D25/'Adjusted close'!D26 -> 1.0249042 | E29: ='Adjusted close'!E25/'Adjusted close'!E26 -> 0.93804285 | F29: ='Adjusted close'!F25/'Adjusted close'!F26 -> 1.0248691 | G29: ='Adjusted close'!G25/'Adjusted close'!G26 -> 0.99495204 | H29: ='Adjusted close'!H25/'Adjusted close'!H26 -> 1.0363423 | I29: ='Adjusted close'!I25/'Adjusted close'!I26 -> 1.0483946 | ... K29: ='Adjusted close'!K25/'Adjusted close'!K26 -> 1.0720254
A30: 40268 | B30: ='Adjusted close'!B26/'Adjusted close'!B27 -> 1.1496678 | C30: ='Adjusted close'!C26/'Adjusted close'!C27 -> 1.0701436 | D30: ='Adjusted close'!D26/'Adjusted close'!D27 -> 1.0858034 | E30: ='Adjusted close'!E26/'Adjusted close'!E27 -> 1.0234074 | F30: ='Adjusted close'!F26/'Adjusted close'!F27 -> 1.0418182 | G30: ='Adjusted close'!G26/'Adjusted close'!G27 -> 1.0117467 | H30: ='Adjusted close'!H26/'Adjusted close'!H27 -> 1.1335548 | I30: ='Adjusted close'!I26/'Adjusted close'!I27 -> 1.1274921 | ... K30: ='Adjusted close'!K26/'Adjusted close'!K27 -> 1.1593186
A31: 40235 | B31: ='Adjusted close'!B27/'Adjusted close'!B28 -> 1.0493289 | C31: ='Adjusted close'!C27/'Adjusted close'!C28 -> 1.0520833 | D31: ='Adjusted close'!D27/'Adjusted close'!D28 -> 1.0665557 | E31: ='Adjusted close'!E27/'Adjusted close'!E28 -> 0.96594161 | F31: ='Adjusted close'!F27/'Adjusted close'!F28 -> 0.97821254 | G31: ='Adjusted close'!G27/'Adjusted close'!G28 -> 0.96051018 | H31: ='Adjusted close'!H27/'Adjusted close'!H28 -> 1.0046729 | I31: ='Adjusted close'!I27/'Adjusted close'!I28 -> 1.0472527 | ... K31: ='Adjusted close'!K27/'Adjusted close'!K28 -> 0.97207792
A32: 40207 | B32: ='Adjusted close'!B28/'Adjusted close'!B29 -> 1.1194146 | C32: ='Adjusted close'!C28/'Adjusted close'!C29 -> 0.98897272 | D32: ='Adjusted close'!D28/'Adjusted close'!D29 -> 0.95094937 | E32: ='Adjusted close'!E28/'Adjusted close'!E29 -> 1.0448565 | F32: ='Adjusted close'!F28/'Adjusted close'!F29 -> 0.91833401 | G32: ='Adjusted close'!G28/'Adjusted close'!G29 -> 0.93359286 | H32: ='Adjusted close'!H28/'Adjusted close'!H29 -> 1.0631654 | I32: ='Adjusted close'!I28/'Adjusted close'!I29 -> 0.98591549 | ... K32: ='Adjusted close'!K28/'Adjusted close'!K29 -> 0.89094591
A33: 40178 | B33: ='Adjusted close'!B29/'Adjusted close'!B30 -> 1.0328497 | C33: ='Adjusted close'!C29/'Adjusted close'!C30 -> 0.97565119 | D33: ='Adjusted close'!D29/'Adjusted close'!D30 -> 1.0621849 | E33: ='Adjusted close'!E29/'Adjusted close'!E30 -> 1.0195122 | F33: ='Adjusted close'!F29/'Adjusted close'!F30 -> 1.0403568 | G33: ='Adjusted close'!G29/'Adjusted close'!G30 -> 1.0141663 | H33: ='Adjusted close'!H29/'Adjusted close'!H30 -> 0.95010115 | I33: ='Adjusted close'!I29/'Adjusted close'!I30 -> 1.0187638 | ... K33: ='Adjusted close'!K29/'Adjusted close'!K30 -> 0.97161327
A34: 40147 | B34: ='Adjusted close'!B30/'Adjusted close'!B31 -> 1.1061079 | C34: ='Adjusted close'!C30/'Adjusted close'!C31 -> 1.1318699 | D34: ='Adjusted close'!D30/'Adjusted close'!D31 -> 1.0124787 | E34: ='Adjusted close'!E30/'Adjusted close'!E31 -> 1.1705924 | F34: ='Adjusted close'!F30/'Adjusted close'!F31 -> 1.0494873 | G34: ='Adjusted close'!G30/'Adjusted close'!G31 -> 1.0375904 | H34: ='Adjusted close'!H30/'Adjusted close'!H31 -> 1.1234848 | I34: ='Adjusted close'!I30/'Adjusted close'!I31 -> 1.0801788 | ... K34: ='Adjusted close'!K30/'Adjusted close'!K31 -> 1.0589286
A35: 40116 | B35: ='Adjusted close'!B31/'Adjusted close'!B32 -> 0.88272334 | C35: ='Adjusted close'!C31/'Adjusted close'!C32 -> 0.88099944 | D35: ='Adjusted close'!D31/'Adjusted close'!D32 -> 0.9767313 | E35: ='Adjusted close'!E31/'Adjusted close'!E32 -> 0.97801047 | F35: ='Adjusted close'!F31/'Adjusted close'!F32 -> 0.96473118 | G35: ='Adjusted close'!G31/'Adjusted close'!G32 -> 0.94640821 | H35: ='Adjusted close'!H31/'Adjusted close'!H32 -> 0.86842105 | I35: ='Adjusted close'!I31/'Adjusted close'!I32 -> 0.96602361 | ... K35: ='Adjusted close'!K31/'Adjusted close'!K32 -> 0.99027409
A36: 40086 | B36: ='Adjusted close'!B32/'Adjusted close'!B33 -> 1.090324 | C36: ='Adjusted close'!C32/'Adjusted close'!C33 -> 1.0413053 | D36: ='Adjusted close'!D32/'Adjusted close'!D33 -> 0.96318036 | E36: ='Adjusted close'!E32/'Adjusted close'!E33 -> 0.98725017 | F36: ='Adjusted close'!F32/'Adjusted close'!F33 -> 1.0370205 | G36: ='Adjusted close'!G32/'Adjusted close'!G33 -> 0.99185705 | H36: ='Adjusted close'!H32/'Adjusted close'!H33 -> 1.1884285 | I36: ='Adjusted close'!I32/'Adjusted close'!I33 -> 1.0107683 | ... K36: ='Adjusted close'!K32/'Adjusted close'!K33 -> 1.1651786
A37: 40056 | B37: ='Adjusted close'!B33/'Adjusted close'!B34 -> 1.1684633 | C37: ='Adjusted close'!C33/'Adjusted close'!C34 -> 1.0105466 | D37: ='Adjusted close'!D33/'Adjusted close'!D34 -> 1.0629609 | E37: ='Adjusted close'!E33/'Adjusted close'!E34 -> 1.080417 | F37: ='Adjusted close'!F33/'Adjusted close'!F34 -> 0.99335401 | G37: ='Adjusted close'!G33/'Adjusted close'!G34 -> 0.99392986 | H37: ='Adjusted close'!H33/'Adjusted close'!H34 -> 1.0373074 | I37: ='Adjusted close'!I33/'Adjusted close'!I34 -> 1.0687403 | ... K37: ='Adjusted close'!K33/'Adjusted close'!K34 -> 1.1634039
A38: 40025 | B38: ='Adjusted close'!B34/'Adjusted close'!B35 -> 1.0096178 | C38: ='Adjusted close'!C34/'Adjusted close'!C35 -> 0.92701735 | D38: ='Adjusted close'!D34/'Adjusted close'!D35 -> 1.1629288 | E38: ='Adjusted close'!E34/'Adjusted close'!E35 -> 1.0735412 | F38: ='Adjusted close'!F34/'Adjusted close'!F35 -> 1.0737393 | G38: ='Adjusted close'!G34/'Adjusted close'!G35 -> 0.99307881 | H38: ='Adjusted close'!H34/'Adjusted close'!H35 -> 1.1437848 | I38: ='Adjusted close'!I34/'Adjusted close'!I35 -> 1.104811 | ... K38: ='Adjusted close'!K34/'Adjusted close'!K35 -> 1.0407484
A39: 39994 | B39: ='Adjusted close'!B35/'Adjusted close'!B36 -> 0.94770928 | C39: ='Adjusted close'!C35/'Adjusted close'!C36 -> 0.96428097 | D39: ='Adjusted close'!D35/'Adjusted close'!D36 -> 1.0527778 | E39: ='Adjusted close'!E35/'Adjusted close'!E36 -> 1.0279376 | F39: ='Adjusted close'!F35/'Adjusted close'!F36 -> 1.0019066 | G39: ='Adjusted close'!G35/'Adjusted close'!G36 -> 1.0666825 | H39: ='Adjusted close'!H35/'Adjusted close'!H36 -> 0.87642276 | I39: ='Adjusted close'!I35/'Adjusted close'!I36 -> 0.94695737 | ... K39: ='Adjusted close'!K35/'Adjusted close'!K36 -> 0.94610543
A40: 39962 | B40: ='Adjusted close'!B36/'Adjusted close'!B37 -> 1.1307296 | C40: ='Adjusted close'!C36/'Adjusted close'!C37 -> 1.0724865 | D40: ='Adjusted close'!D36/'Adjusted close'!D37 -> 1.0048849 | E40: ='Adjusted close'!E36/'Adjusted close'!E37 -> 1.1373832 | F40: ='Adjusted close'!F36/'Adjusted close'!F37 -> 0.96771218 | G40: ='Adjusted close'!G36/'Adjusted close'!G37 -> 1.0515903 | H40: ='Adjusted close'!H36/'Adjusted close'!H37 -> 1.0658579 | I40: ='Adjusted close'!I36/'Adjusted close'!I37 -> 1.0726003 | ... K40: ='Adjusted close'!K36/'Adjusted close'!K37 -> 0.95888344
... A127: 37315 | B127: ='Adjusted close'!B123/'Adjusted close'!B124 -> 1.1268204 | C127: ='Adjusted close'!C123/'Adjusted close'!C124 -> 1.0670602 | D127: ='Adjusted close'!D123/'Adjusted close'!D124 -> 0.81520223 | E127: ='Adjusted close'!E123/'Adjusted close'!E124 -> 1.0364362 | F127: ='Adjusted close'!F123/'Adjusted close'!F124 -> 1.0107431 | G127: ='Adjusted close'!G123/'Adjusted close'!G124 -> 1.0094229 | H127: ='Adjusted close'!H123/'Adjusted close'!H124 -> 1.0410237 | I127: ='Adjusted close'!I123/'Adjusted close'!I124 -> 1.1404927 | ... K127: ='Adjusted close'!K123/'Adjusted close'!K124 -> 1.0754887

Sheet Correlation effect
A2: Budget | B2: 10000
A4: Monthly interest rate | B4: =(1.01^(1/12)-1)*100 -> 0.082953811 | C4: percentile points
B6: Boeing Cie | C6: Lockheed Martin | D6: Intel Corp. | E6: Merck & Company | F6: AT&T | G6: Exelon | H6: GE | I6: Honeywell | J6: Schlumberger | K6: Avery | L6: Cash | O6: Investment id
A7: Investment | B7: =VLOOKUP($O$7,$A$33:$L$35,2,FALSE) -> 1000 | C7: =VLOOKUP($O$7,$A$33:$L$35,3,FALSE) -> 1000 | D7: =VLOOKUP($O$7,$A$33:$L$35,4,FALSE) -> 1000 | E7: =VLOOKUP($O$7,$A$33:$L$35,5,FALSE) -> 1000 | F7: =VLOOKUP($O$7,$A$33:$L$35,6,FALSE) -> 1000 | G7: =VLOOKUP($O$7,$A$33:$L$35,7,FALSE) -> 1000 | H7: =VLOOKUP($O$7,$A$33:$L$35,8,FALSE) -> 1000 | I7: =VLOOKUP($O$7,$A$33:$L$35,9,FALSE) -> 1000 | J7: =VLOOKUP($O$7,$A$33:$L$35,10,FALSE) -> 1000 | K7: =VLOOKUP($O$7,$A$33:$L$35,11,FALSE) -> 1000 | L7: =VLOOKUP($O$7,$A$33:$L$35,12,FALSE) -> 0 | M7: =SUM(B7:L7) -> 10000 | O7: =_xll.RiskCurrentSim() -> 1
A8: Minimum | B8: 0 | C8: =$B$8 -> 0 | D8: =$B$8 -> 0 | E8: =$B$8 -> 0 | F8: =$B$8 -> 0 | G8: =$B$8 -> 0 | H8: =$B$8 -> 0 | I8: =$B$8 -> 0 | J8: =$B$8 -> 0 | K8: =$B$8 -> 0 | L8: 0 | M8: =
A9: Maximum | B9: =B2 -> 10000 | C9: =$B$9 -> 10000 | D9: =$B$9 -> 10000 | E9: =$B$9 -> 10000 | F9: =$B$9 -> 10000 | G9: =$B$9 -> 10000 | H9: =$B$9 -> 10000 | I9: =$B$9 -> 10000 | J9: =$B$9 -> 10000 | K9: =$B$9 -> 10000 | L9: =B2 -> 10000 | M9: =B2 -> 10000
A11: Returns model | B11: Log normal | C11: Log normal | D11: Log normal | E11: Log normal | F11: Log normal | G11: Log normal | H11: Log normal | I11: Log normal | J11: Log normal | K11: Log normal
A12: mean | B12: ='Return rate'!B3 -> 1.0102 | C12: ='Return rate'!C3 -> 1.0084 | D12: ='Return rate'!D3 -> 1.0044 | E12: ='Return rate'!E3 -> 1.0032 | F12: ='Return rate'!F3 -> 1.0049 | G12: ='Return rate'!G3 -> 1.0082 | H12: ='Return rate'!H3 -> 1.0011 | I12: ='Return rate'!I3 -> 1.0103 | ... K12: ='Return rate'!K3 -> 1.0004
A13: std dev | B13: ='Return rate'!B4 -> 0.08265 | C13: ='Return rate'!C4 -> 0.067323 | D13: ='Return rate'!D4 -> 0.099085 | E13: ='Return rate'!E4 -> 0.078483 | F13: ='Return rate'!F4 -> 0.068432 | G13: ='Return rate'!G4 -> 0.051797 | H13: ='Return rate'!H4 -> 0.086978 | I13: ='Return rate'!I4 -> 0.082517 | ... K13: ='Return rate'!K4 -> 0.082606
A15: Without correlation
A16: Returns | L16: =1+B4/100 -> 1.0008295
A17: Cash received | B17: =B16*B7 -> 0 | C17: =C16*C7 -> 0 | D17: =D16*D7 -> 0 | E17: =E16*E7 -> 0 | F17: =F16*F7 -> 0 | G17: =G16*G7 -> 0 | H17: =H16*H7 -> 0 | I17: =I16*I7 -> 0 | ... L17: =L16*L7 -> 0
A19: Total Return (in pp) | B19: =(SUM(B17:L17)/$B$2-1)*100 -> -100
A20: Mean
A21: Std Dev
A24: With correlation
A25: Returns | L25: =1+B4/100 -> 1.0008295
A26: Cash received | B26: =B25*B7 -> 0 | C26: =C25*C7 -> 0 | D26: =D25*D7 -> 0 | E26: =E25*E7 -> 0 | F26: =F25*F7 -> 0 | G26: =G25*G7 -> 0 | H26: =H25*H7 -> 0 | I26: =I25*I7 -> 0 | ... L26: =L25*L7 -> 0
A28: Total Return (in pp) | B28: =(SUM(B26:L26)/$B$2-1)*100 -> -100
A29: Mean | B29: =_xll.RiskMean(B28) -> -100
A30: Std Dev | B30: =_xll.RiskStdDev(B28) -> 0
M31: Exp return | N31: Std. dev. (in pp)
A32: Investment policy id | M32: (in pp) | N32: no correl. | O32: correl | P32: improv. (%)
A33: 1 | B33: 1000 | C33: 1000 | D33: 1000 | E33: 1000 | F33: 1000 | G33: 1000 | H33: 1000 | I33: 1000 | J33: 1000 | K33: 1000 | L33: 0 | M33: =_xll.RiskMean($B$19,A33) -> -100 | N33: =_xll.RiskStdDev($B$19,A33) -> 0 | O33: =_xll.RiskStdDev($B$28,A33) -> 0 | P33: 0
A34: 2 | B34: 850 | C34: 1040 | D34: 230 | E34: 240 | F34: 520 | G34: 1700 | H34: 10 | I34: 880 | J34: 860 | K34: 0 | L34: =$B$2-SUM(B34:K34) -> 3670 | M34: =_xll.RiskMean($B$19,A34) -> #N/A | N34: =_xll.RiskStdDev($B$19,A34) -> #N/A | O34: =_xll.RiskStdDev($B$28,A34) -> #N/A | P34: =-(O34-O33)/O33 -> #N/A
A35: 3 | B35: 460 | C35: 1420 | D35: 0 | E35: 0 | F35: 0 | G35: 2760 | H35: 0 | I35: 0 | J35: 1200 | K35: 0 | L35: =$B$2-SUM(B35:K35) -> 4160 | M35: =_xll.RiskMean($B$19,A35) -> #N/A | N35: =_xll.RiskStdDev($B$19,A35) -> #N/A | O35: =_xll.RiskStdDev($B$28,A35) -> #N/A | P35: =-(O35-O34)/O34 -> #N/A

Sheet ro_HiddenInfo
A1: Goal (Cell, Statistic, Parameter), E1: RO Formula to Optimize | B1: =#REF! -> #REF! | C1: 2 | D1: 0.5 | F1: MACROS | I1: Compatibility with Old Versions (4 trips pre-v5 versions) | J1: 4 | L1: RISKOpt Tag | M1: TRUE | O1: Out Stats | Y1: VERSION 6.0 SETTINGS | AA1: EFFICIENT FRONTIER | AD1: EF Stopping Conditions
A2: Goal (Type, Target Value) | B2: 1 | C2: 0 | F2: Start (enabled, macro) | G2: FALSE | I2: Formula Conversion Cell (not used in v5) | L2: #Iterations - Sim Stopping (legacy setting used in v5 and earlier)) | M2: 1000 | O2: Mean | R2: Creation Version | S2: 5.7.1 | U2: Constraint Solver, number of Latin Hypercube stratifications, for reproducing results with Actual Convergence | X2: Optimization Engine | Y2: 0 | AA2: Analysis Type (Standard vs. Efficient Frontier) | AB2: 0 | AD2: EF Stop on Trials | AE2: TRUE
A3: Trial Count Stopping (enabled, trial count) | B3: FALSE | C3: 1000 | F3: Before Recalc (enabled, macro), starting with v6 RISKOptimizer uses corresponding @RISK macro | G3: FALSE | I3: Number Formatting Cell (introduced in v5) | J3: 0 | L3: Sim. Stopping Mode, Tolerance (legacy settings used in v5 and earlier) | M3: 0 | N3: 0 | O3: Std. Dev. | R3: Required Version | S3: 5.0.0 | U3: Constraint Solver, total of adjustable cell values, to only pass number of stratifications if model hasn't changed | X3: Mutation Rate (becoming a single settings for all adjustable cell groups) | Y3: 0.1 | AA3: EF Item to Constrain | AD3: EF Trial Count | AE3: 250
A4: Timespan Stopping (enabled, trial count) | B4: TRUE | C4: 8 | D4: 1 | F4: After Recalc (enabled, macro), starting with v6 RISKOptimizer uses corresponding @RISK macro | G4: FALSE | L4: Same Seed Each Simulation (this was used in RISKOptimizer version 5 and earlier) | M4: TRUE | O4: Min | R4: Recommended Version | S4: 1.0.0 | X4: Crossover Rate (becoming a single settings for all adjustable cell groups) | Y4: 0.5 | AA4: EF Constraint Minimum | AD4: EF Stop on Time | AE4: FALSE
A5: Progress Stopping (enabled, trial count, max % change, change is percent) | B5: FALSE | C5: 100 | D5: 0.01 | E5: TRUE | F5: After Storage (enabled, macro) | G5: FALSE | L5: Sampling Type (this was used in RISKOptimizer version 5 and earlier) | M5: 3 | O5: Max | R5: Last Modified by Version | S5: 7.5.2 | X5: Genetic Operators (becoming a single settings for all adjustable cell groups) | Y5: 1,1,1,1,1,1,1,1,1,1,1 | AA5: EF Constraint Maximum | AD5: EF Time Duration | AE5: 15
A6: Formula Stopping (enabled, formula) | B6: FALSE | C6: =IF(_xll.RiskStdDev(#REF!)<=1.1,TRUE,FALSE) -> #REF! | F6: Finish (enabled, macro) | G6: FALSE | L6: Macro Before Simulation (enabled, macro), starting with v6, this is legacy setting | M6: FALSE | R6: Genetic Algorithm - Discrete Variable Warning Shown | X6: Stopping on Projected Convergence (added in version 6; other simulation runtime settings got moved to @RISK) | Y6: TRUE | AA6: EF Formula for Dtools | AD6: EF Time Unit | AE6: 2
A7: Population Size | B7: 50 | L7: Macro After Simulation (enabled, macro), starting with v6, this is legacy setting | M7: FALSE | R7: ColorOptimizationCells Called | AD7: EF Stop on Progress | AE7: FALSE
A8: UNUSED | B8: UNUSED | F8: Seed (Is Auto, Value) | G8: TRUE | H8: 1 | AD8: EF Trials (Progress) | AE8: 100
A9: Ev4/RO1: Update Display (replaced by Show Excel Recalcs in v5) | B9: 3 | F9: Minimize Excel on Startup | G9: FALSE | AD9: EF Max. Change (Progress) | AE9: 0.01
A10: Stop on Errors (before v5: Pause on Errors) | B10: FALSE | AD10: EF Max. Change is Percent (Progress) | AE10: TRUE
A11: Keep Trial-by-Trial Log (if cell has anything other than False consider True, since Evolver 4 didn't have this setting); this setting no longer used staring with version 6 | B11: TRUE
A12: Ev4/RO1: Graph Progress | B12: FALSE | F12: Show Excel Recalcs (replaces "Update Display" used before v5) | G12: 2
A14: # Chromosomes | B14: 1 | AX14: # Constraints | AY14: 2
A15: Method + #Operators(Legacy) | B15: Mutation Rate (Legacy) | C15: Crossover Rate (Legacy) | D15: Description | E15: # Time Blocks/All Groups Must Be Present | F15: Constraint Range | G15: #Ranges | H15: Adj. Range | I15: Min Val or Range | J15: Max Val Or Range | K15: Flags | AR15: HARD CONSTRAINT DEV | AS15: CONSTRAINT SOLVER | AT15: ROFUNC | AU15: RISKOPT | AV15: SOFT CONSTRAINT DEV | AW15: EVAL (True/False or penalty) | AX15: Type (Hard/Soft) | AY15: Entry Mode | AZ15: Formula | BA15: Description | BB15: Left Val Or Range | BC15: Left Operator | BD15: Constrained Cells | BE15: Right Operator | BF15: Right Val Or Range | BG15: Penalty Function | BH15: RO Eval Time (Iter/Sim) | BI15: RO Statistic to Constrain | BJ15: RO Statistic Parameter | BK15: Precision (added 6.0) | BL15: RO Auto Eval Time (added 6.0) | BM15: Is Disabled | BN15: Use for EF | BO15: EF Settings Have Been Defined | BP15: EF Location of Constraining Values | BQ15: EF Min Constraining Value | BR15: EF Max Constraining Value | BS15: EF # of Constraining Values Between Min and Max | BT15: EF Range with Constraining Values | BU15: EF # of Constraining Values Listed
A16: RECIPE_x0001_11 | B16: 0.1 | C16: 0.5 | G16: 1 | H16: =#REF! -> #REF! | I16: 0 | J16: =#REF! -> #REF! | K16: False,False,False | AX16: 2 | AY16: 1 | BA16: Minimum Exp Return | BB16: =#REF! -> #REF! | BC16: 2 | BD16: =#REF! -> #REF! | BE16: 2 | BF16: 100 | BH16: 1 | BI16: 1 | BJ16: 0
A17: DEFAULT PARENT SELECTION | AX17: 2 | AY17: 1 | BA17: Budget | BB17: 0 | BC17: 6 | BD17: =#REF! -> #REF! | BE17: 4 | BF17: 0 | BH17: 1 | BI17: 12 | BJ17: 0
A18: DEFAULT MUTATION
A19: DEFAULT CROSSOVER
A20: DEFAULT BACKTRACK
A21: ARITHMETIC CROSSOVER
A22: HEURISTIC CROSSOVER
A23: CAUCHY MUTATION
A24: BOUNDARY MUTATION
A25: NON-UNIFORM MUTATION
A26: LINEAR
A27: LOCAL SEARCH
